areaCalculatingLib/__init__.py
areaCalculatingLib/area.py
area_calculation-0.0.2.dist-info/METADATA
area_calculation-0.0.2.dist-info/WHEEL
area_calculation-0.0.2.dist-info/top_level.txt
area_calculation-0.0.2.dist-info/RECORD
