Metadata-Version: 2.1
Name: area-calculation
Version: 0.0.2
Summary: library for finding the area of a circle and a triangle
Home-page: https://github.com/ylerby/areaCalculatingLib
Author: ylerby
Author-email: WeaklyFob@yandex.ry
Project-URL: GitHub, https://github.com/ylerby/areaCalculatingLib
Keywords: files area
Classifier: Programming Language :: Python :: 3.9
Requires-Python: >=3.6
Requires-Dist: pytest
